sphinx_gherkindoc/__init__.py
sphinx_gherkindoc/cli.py
sphinx_gherkindoc/files.py
sphinx_gherkindoc/glossary.py
sphinx_gherkindoc/parsers/__init__.py
sphinx_gherkindoc/parsers/base.py
sphinx_gherkindoc/parsers/behave.py
sphinx_gherkindoc/parsers/pytest_bdd.py
sphinx_gherkindoc/sample-conf.py
sphinx_gherkindoc/utils.py
sphinx_gherkindoc/writer.py
sphinx_gherkindoc-3.6.4.dist-info/entry_points.txt
sphinx_gherkindoc-3.6.4.dist-info/WHEEL
sphinx_gherkindoc-3.6.4.dist-info/METADATA
sphinx_gherkindoc-3.6.4.dist-info/RECORD
