Metadata-Version: 2.1
Name: sphinx-gherkindoc
Version: 3.6.4
Summary: A tool to convert Gherkin into Sphinx documentation
Home-page: https://jolly-good-toolbelt.github.io/sphinx_gherkindoc/
License: MIT
Author: Lewis Franklin
Author-email: lewis.franklin@gmail.com
Requires-Python: >=3.6.1,<4.0.0
Classifier: License :: OSI Approved :: MIT License
Classifier: Programming Language :: Python :: 3
Classifier: Programming Language :: Python :: 3.10
Classifier: Programming Language :: Python :: 3.7
Classifier: Programming Language :: Python :: 3.8
Classifier: Programming Language :: Python :: 3.9
Requires-Dist: Sphinx (>=1.3)
Requires-Dist: behave (>=1.2.6)
Requires-Dist: recommonmark (>=0.4.0)
Requires-Dist: sphinx_rtd_theme (>=0.3.1)
Requires-Dist: typing_extensions (>=3.7.4,<4.0.0); python_version < "3.8"
Project-URL: Documentation, https://jolly-good-toolbelt.github.io/sphinx_gherkindoc/
Project-URL: Repository, https://github.com/jolly-good-toolbelt/sphinx_gherkindoc
